testpkg/__init__.py
kanimus_py-0.0.1.dist-info/METADATA
kanimus_py-0.0.1.dist-info/WHEEL
kanimus_py-0.0.1.dist-info/top_level.txt
kanimus_py-0.0.1.dist-info/RECORD
